leopardo/__init__.py
leopardo/__main__.py
leopardo/_version.py
leopardo/app.py
leopardo-0.0.5.dist-info/LICENSE
leopardo-0.0.5.dist-info/METADATA
leopardo-0.0.5.dist-info/WHEEL
leopardo-0.0.5.dist-info/entry_points.txt
leopardo-0.0.5.dist-info/top_level.txt
leopardo-0.0.5.dist-info/RECORD
