Metadata-Version: 2.1
Name: leopardo
Version: 0.0.5
Summary: Configurable fast-access toolset
Home-page: https://github.com/es7s/leopardo
Author: Aleksandr Shavykin
Author-email: 0.delameter@gmail.com
Classifier: Environment :: Console
Classifier: Intended Audience :: Developers
Classifier: Intended Audience :: Science/Research
Classifier: Intended Audience :: System Administrators
Classifier: Programming Language :: Python :: 3
Classifier: License :: OSI Approved :: MIT License
Classifier: Operating System :: OS Independent
Requires-Python: >=3.7
License-File: LICENSE
Requires-Dist: pytermor
